beakerx_kotlin/__init__.py
beakerx_kotlin/_version.py
beakerx_kotlin/commands.py
beakerx_kotlin/install.py
beakerx_kotlin/kernel/kernel.json
beakerx_kotlin/kernel/logo-32x32.png
beakerx_kotlin/kernel/logo-64x64.png
beakerx_kotlin/kernel/ext/beakerx-runtimetools-1.6-SNAPSHOT.jar
beakerx_kotlin/kernel/ext/beakerx-runtimetools-2.0-SNAPSHOT.jar
beakerx_kotlin/kernel/lib/annotations-13.0.jar
beakerx_kotlin/kernel/lib/assertj-core-3.6.1.jar
beakerx_kotlin/kernel/lib/beakerx-kernel-base-1.6-SNAPSHOT.jar
beakerx_kotlin/kernel/lib/beakerx-kernel-base-2.0-SNAPSHOT.jar
beakerx_kotlin/kernel/lib/beakerx-kernel-base-api-1.6-SNAPSHOT.jar
beakerx_kotlin/kernel/lib/beakerx-kernel-base-api-2.0-SNAPSHOT.jar
beakerx_kotlin/kernel/lib/commons-beanutils-1.9.3.jar
beakerx_kotlin/kernel/lib/commons-cli-1.2.jar
beakerx_kotlin/kernel/lib/commons-codec-1.10.jar
beakerx_kotlin/kernel/lib/commons-collections-3.2.2.jar
beakerx_kotlin/kernel/lib/commons-io-2.5.jar
beakerx_kotlin/kernel/lib/commons-lang3-3.6.jar
beakerx_kotlin/kernel/lib/commons-logging-1.2.jar
beakerx_kotlin/kernel/lib/commons-text-1.1.jar
beakerx_kotlin/kernel/lib/fluent-hc-4.5.5.jar
beakerx_kotlin/kernel/lib/gson-2.3.1.jar
beakerx_kotlin/kernel/lib/hamcrest-core-1.3.jar
beakerx_kotlin/kernel/lib/httpclient-4.5.5.jar
beakerx_kotlin/kernel/lib/httpcore-4.4.9.jar
beakerx_kotlin/kernel/lib/ivy-2.4.0.jar
beakerx_kotlin/kernel/lib/jackson-annotations-2.6.0.jar
beakerx_kotlin/kernel/lib/jackson-core-2.6.5.jar
beakerx_kotlin/kernel/lib/jackson-databind-2.6.5.jar
beakerx_kotlin/kernel/lib/javalin-1.7.0.jar
beakerx_kotlin/kernel/lib/javax.servlet-api-3.1.0.jar
beakerx_kotlin/kernel/lib/jeromq-0.3.5.jar
beakerx_kotlin/kernel/lib/jetty-client-9.4.9.v20180320.jar
beakerx_kotlin/kernel/lib/jetty-http-9.4.9.v20180320.jar
beakerx_kotlin/kernel/lib/jetty-io-9.4.9.v20180320.jar
beakerx_kotlin/kernel/lib/jetty-security-9.4.9.v20180320.jar
beakerx_kotlin/kernel/lib/jetty-server-9.4.9.v20180320.jar
beakerx_kernel_kotlin-2.0.0.dist-info/METADATA
beakerx_kernel_kotlin-2.0.0.dist-info/WHEEL
beakerx_kernel_kotlin-2.0.0.dist-info/entry_points.txt
beakerx_kernel_kotlin-2.0.0.dist-info/top_level.txt
beakerx_kernel_kotlin-2.0.0.dist-info/RECORD
